sincpro_log/__init__.py
sincpro_log/domain/__init__.py
sincpro_log/infrastructure/__init__.py
sincpro_log/logger.py
sincpro_log/use_cases/__init__.py
sincpro_log-1.0.1.dist-info/LICENSE.md
sincpro_log-1.0.1.dist-info/METADATA
sincpro_log-1.0.1.dist-info/WHEEL
sincpro_log-1.0.1.dist-info/RECORD
