Metadata-Version: 2.3
Name: sincpro-log
Version: 1.0.1
Summary: A logging module for sincpro applications
License: LICENSE.md
Author: Andres Gutierrez
Author-email: andru1236@gmail.com
Requires-Python: >=3.12,<4.0
Classifier: License :: Other/Proprietary License
Classifier: Programming Language :: Python :: 3
Classifier: Programming Language :: Python :: 3.12
Classifier: Programming Language :: Python :: 3.13
Requires-Dist: structlog (>=25.4.0,<26.0.0)
